{"Language":["en"],"Header":{"Status":"true","Logo":{"Title":"","Text":"","ImageURI":""},"Social":[{"Text":"wadawd","Icone":"https://raw.githubusercontent.com/artafps/artafps/main/social/jpg/icon-f-f.png","Link":"awdwad"},{"Text":"awdawd","Icone":"https://raw.githubusercontent.com/artafps/artafps/main/donate/jpg/Dicone-f-f.png","Link":"awdawdawd"}]},"Slider":{"Status":"false","H1Text":"","Description":"","BtnText":"","LinkBtn":"","ImageURI1":"","ImageURI2":"","TextCircle":"","LinkCircle":""},"Skils":{"Status":"true","Arr":[{"Text":"awdawdwad","Icone":"https://raw.githubusercontent.com/artafps/artafps/main/Skils/jpg/Dicone-f-f.png"}]},"News":{"Status":"","Title":"","Arr":[{"TopTitle":"","Title":"","SubTitle":"","BtnText":"","LinkBtn":"","Direction":""}]},"Blog":{"Status":"","Title":""},"Project":{"Status":"","Title":"","Arr":[{"Title":"","ImageURI":"","Description":"","Link":""}]},"Plan":{"Status":"","Title":"","Arr":[{"TopTitle":"","Title":"","Percent":"","Description":""}]},"Footer":{"Status":"true","Logo":{"Title":"awdwadwd","Text":"artafs","ImageURI":"https://api.github.com/repos/artafps/artafps/contents/logo/logoFooter-f-IMG_20220521_134731.jpg"},"Social":[],"PowerBy":{"Status":"true","Text":"wadawd","Link":"wadawd"}},"Community":{"Status":"","Text":"","BtnText":"","LinkBtn":""},"Team":{"Status":"","Title":"","Arr":[{"Image":"","Name":"","Social":[{"Icone":"","Link":""}]}]},"Donate":{"Status":"true","Title":"atata","SubTitle":"artawdwa","Items":[{"Text":"awdawdwad","Icone":"https://raw.githubusercontent.com/artafps/artafps/main/Skils/jpg/Dicone-f-f.png"}]}}